owasp_dependency_track_cli-1.0.10.dist-info/licenses/LICENSE
owasp_dt_cli/__init__.py
owasp_dt_cli/analyze.py
owasp_dt_cli/api.py
owasp_dt_cli/arguments.py
owasp_dt_cli/cli.py
owasp_dt_cli/common.py
owasp_dt_cli/config.py
owasp_dt_cli/log.py
owasp_dt_cli/metrics.py
owasp_dt_cli/models.py
owasp_dt_cli/project.py
owasp_dt_cli/prometheus.py
owasp_dt_cli/report.py
owasp_dt_cli/test.py
owasp_dt_cli/upload.py
owasp_dependency_track_cli-1.0.10.dist-info/METADATA
owasp_dependency_track_cli-1.0.10.dist-info/WHEEL
owasp_dependency_track_cli-1.0.10.dist-info/entry_points.txt
owasp_dependency_track_cli-1.0.10.dist-info/top_level.txt
owasp_dependency_track_cli-1.0.10.dist-info/RECORD
