Metadata-Version: 2.4
Name: owasp-dependency-track-cli
Version: 1.0.10
Summary: Inofficial OWASP Dependency Track CLI
Requires-Python: >=3.13
License-File: LICENSE
Requires-Dist: owasp-dependency-track-client==4.13.7
Requires-Dist: is_empty==1.0.1
Requires-Dist: tinystream==0.1.18
Requires-Dist: tabulate==0.9.0
Requires-Dist: colorama==0.4.6
Requires-Dist: dotenv==0.9.9
Requires-Dist: prometheus-client==0.21.1
Provides-Extra: build
Requires-Dist: build; extra == "build"
Requires-Dist: twine; extra == "build"
Provides-Extra: test
Requires-Dist: pytest>=7; extra == "test"
Requires-Dist: pytest-depends; extra == "test"
Requires-Dist: pytest-cov; extra == "test"
Dynamic: license-file
